knifes/__init__.py
knifes/aes.py
knifes/digests.py
knifes/exception_handlers.py
knifes/media.py
knifes/network.py
knifes/operators.py
knifes/package.py
knifes/shell.py
knifes/strings.py
knifes/times.py
knifes/urls.py
knifes/useragent.py
knifes/deploy/__init__.py
knifes/deploy/celery.py
knifes/deploy/main.py
knifes-1.0.2.dist-info/METADATA
knifes-1.0.2.dist-info/WHEEL
knifes-1.0.2.dist-info/top_level.txt
knifes-1.0.2.dist-info/RECORD
